datasette_scale_to_zero/__init__.py
datasette_scale_to_zero-0.3.2.dist-info/WHEEL
datasette_scale_to_zero-0.3.2.dist-info/entry_points.txt
datasette_scale_to_zero-0.3.2.dist-info/METADATA
datasette_scale_to_zero-0.3.2.dist-info/RECORD
