Metadata-Version: 2.4
Name: datasette-scale-to-zero
Version: 0.3.2
Summary: Quit Datasette if it has not received traffic for a specified time period
Author: Simon Willison
License-Expression: Apache-2.0
Classifier: Framework :: Datasette
Requires-Dist: datasette
Requires-Python: >=3.10
Project-URL: Homepage, https://github.com/simonw/datasette-scale-to-zero
Project-URL: Changelog, https://github.com/simonw/datasette-scale-to-zero/releases
Project-URL: Issues, https://github.com/simonw/datasette-scale-to-zero/issues
Project-URL: CI, https://github.com/simonw/datasette-scale-to-zero/actions
